pgfast/__init__.py
pgfast/cli.py
pgfast/config.py
pgfast/connection.py
pgfast/exceptions.py
pgfast/fastapi.py
pgfast/fixtures.py
pgfast/migrations.py
pgfast/pytest.py
pgfast/schema.py
pgfast/testing.py
pgfast-0.7.1.dist-info/WHEEL
pgfast-0.7.1.dist-info/entry_points.txt
pgfast-0.7.1.dist-info/METADATA
pgfast-0.7.1.dist-info/RECORD
