Metadata-Version: 2.3
Name: pgfast
Version: 0.7.1
Summary: Lightweight PostgreSQL migration and testing toolkit for FastAPI with raw SQL, dependency management, and isolated test databases
Author: Marius Räsener
Author-email: Marius Räsener <931919+elmcrest@users.noreply.github.com>
Classifier: Development Status :: 3 - Alpha
Classifier: Intended Audience :: Developers
Classifier: Topic :: Software Development :: Libraries :: Python Modules
Classifier: Topic :: Database
Classifier: Topic :: Database :: Database Engines/Servers
Classifier: Framework :: AsyncIO
Classifier: Framework :: FastAPI
Classifier: Framework :: Pytest
Classifier: Programming Language :: Python :: 3.14
Classifier: Programming Language :: SQL
Classifier: License :: OSI Approved :: MIT License
Classifier: Operating System :: OS Independent
Classifier: Typing :: Typed
Classifier: Natural Language :: English
Classifier: Environment :: Console
Classifier: Topic :: Software Development :: Testing
Classifier: Topic :: Software Development :: Libraries
Requires-Dist: asyncpg>=0.30.0
Requires-Dist: fastapi>=0.121.2
Requires-Python: >=3.14
Project-URL: Homepage, https://github.com/elmcrest/pgfast
Project-URL: Issues, https://github.com/elmcrest/pgfast/issues
Project-URL: Repository, https://github.com/elmcrest/pgfast
